{
  "users": [
    {
      "userID": "105759860208979968",
      "streaks": [
        {
          "channelName": "art",
          "streakLevel": 3,
          "bestStreak": 3
        }
      ],
      "messagesEnabled": true,
      "mentionsEnabled": true
    },
    {
      "userID": "158620410424852481",
      "streaks": [
        {
          "channelName": "art",
          "streakLevel": 0,
          "bestStreak": 5
        }
      ],
      "messagesEnabled": true,
      "mentionsEnabled": true
    }
  ],
  "streaks": [
    {
      "streakID": "14de3868-b75f-4397-b6f0-7946dcaeffdc",
      "userID": "105759860208979968",
      "messageID": "565552581779259392",
      "channelName": "art",
      "date": "2019-04-09T15:04:03.041Z",
      "content": "awooaegsrjgofnlaekjgfsøædfljgfds"
    },
    {
      "streakID": "df1b6c32-3468-4e3f-a98f-9e59b425537c",
      "userID": "158620410424852481",
      "messageID": "565566356712456192",
      "channelName": "art",
      "date": "2019-04-07T15:58:47.263Z",
      "content": "afdhjgkluiuøkjmngfdgrthykulik"
    },
    {
      "streakID": "cfc5f60b-c81f-4734-b845-3f8b4adf999c",
      "userID": "105759860208979968",
      "messageID": "565566515898875907",
      "channelName": "art",
      "date": "2019-04-08T15:59:25.259Z",
      "content": "afdhjgkluiuøkjmngfdgrthykulik"
    },
    {
      "streakID": "a562c8e3-3005-4cc4-b194-754f2d4a6fc0",
      "userID": "105759860208979968",
      "messageID": "565566654881202186",
      "channelName": "art",
      "date": "2019-04-07T15:59:58.334Z",
      "content": "afdhjgkluiuøkjmngfdgrthykulik"
    },
    {
      "streakID": "4bdc278d-0b4b-47da-a7e7-969276383517",
      "userID": "105759860208979968",
      "messageID": "565567976863039499",
      "channelName": "art",
      "date": "2019-04-06T16:05:13.626Z",
      "content": "hey now, you're an all star, get your game on, go, play\"'}, {"
    },
    {
      "streakID": "eef8689a-c3ce-47f7-814b-002166803c9a",
      "userID": "158620410424852481",
      "messageID": "565591852687032331",
      "channelName": "art",
      "date": "2019-04-10T17:40:05.130Z",
      "content": "i did a thing totally i don't just want a streak"
    }
  ],
  "channels": [
    "art",
    "design",
    "gameplay",
    "music",
    "level-design",
    "production",
    "writing",
    "testland"
  ],
  "configs": [
    {
      "guild": "184112939056365568",
      "top": "372974199943462913",
      "active": "372974199943462913"
    }
  ]
}